pricelevels/__init__.py
pricelevels/_abstract.py
pricelevels/cluster.py
pricelevels/exceptions.py
pricelevels/version.py
pricelevels/scoring/__init__.py
pricelevels/scoring/abstract.py
pricelevels/scoring/touch_scorer.py
pricelevels/visualization/__init__.py
pricelevels/visualization/_helpers.py
pricelevels/visualization/levels_on_candlestick.py
pricelevels/visualization/levels_with_zigzag.py
pricelevels-0.0.4.dist-info/METADATA
pricelevels-0.0.4.dist-info/WHEEL
pricelevels-0.0.4.dist-info/top_level.txt
pricelevels-0.0.4.dist-info/RECORD
